pysmoove/__init__.py
pysmoove/pysmoove.py
pysmoove-0.0.1.dist-info/LICENSE
pysmoove-0.0.1.dist-info/METADATA
pysmoove-0.0.1.dist-info/WHEEL
pysmoove-0.0.1.dist-info/entry_points.txt
pysmoove-0.0.1.dist-info/top_level.txt
pysmoove-0.0.1.dist-info/RECORD
