Metadata-Version: 2.1
Name: pysmoove
Version: 0.0.1
Summary: Execute the population-level SV calling workflow for smoove
Home-page: https://gitlab.com/salk-tm/pysmoove
Author: Anthony Aylward
Author-email: aaylward@salk.edu
License: UNKNOWN
Platform: UNKNOWN
Classifier: Programming Language :: Python :: 3
Classifier: License :: OSI Approved :: MIT License
Classifier: Operating System :: OS Independent
License-File: LICENSE
